Metadata-Version: 1.1
Name: ilock
Version: 1.0.1
Summary: Inter-process named lock library
Home-page: https://github.com/symonsoft/ilock
Author: SymonSoft
Author-email: symonsoft@gmail.com
License: UNKNOWN
Download-URL: https://github.com/symonsoft/ilock/tarball/1.0.1
Keywords: interprocess,multiprocessing,lock,mutex,os-independent
Platform: UNKNOWN
Classifier: Development Status :: 5 - Production/Stable
Classifier: License :: OSI Approved :: BSD License
Classifier: Operating System :: POSIX :: Linux
Classifier: Operating System :: Microsoft :: Windows
Classifier: Programming Language :: Python :: 2
Classifier: Programming Language :: Python :: 2.7
Classifier: Programming Language :: Python :: 3
Classifier: Programming Language :: Python :: 3.3
Classifier: Programming Language :: Python :: 3.4
Classifier: Programming Language :: Python :: 3.5
Classifier: Programming Language :: Python :: 3.6
Classifier: Topic :: Utilities
